LICENSE
README.rst
setup.py
orm_generator/__init__.py
orm_generator/base.py
orm_generator/mysql.py
orm_generator/postgresql.py
orm_generator/sqlit.py
sqlx_orm_generator.egg-info/PKG-INFO
sqlx_orm_generator.egg-info/SOURCES.txt
sqlx_orm_generator.egg-info/dependency_links.txt
sqlx_orm_generator.egg-info/not-zip-safe
sqlx_orm_generator.egg-info/requires.txt
sqlx_orm_generator.egg-info/top_level.txt