Metadata-Version: 2.1
Name: sqlx-orm-generator
Version: 0.0.2
Summary: sqlx-orm-generator is a model code generator from tables for sqlx-orm_generator.
Home-page: https://gitee.com/summry/sqlx-orm-generator
Author: summry
Author-email: xiazhongbiao@126.com
License: UNKNOWN
Keywords: MySQL,mysqlx,python
Platform: UNKNOWN
Requires-Python: >=3.5
License-File: LICENSE
